npv/__init__.py
npv/build_periods.py
npv/change_numbers.py
npv/histogram.py
npv/monthly_cashflow.py
npv/monthly_to_annual.py
npv/npv.py
npv/params.py
npv/salary_calculator.py
npv-0.4.1.dist-info/LICENSE
npv-0.4.1.dist-info/METADATA
npv-0.4.1.dist-info/WHEEL
npv-0.4.1.dist-info/top_level.txt
npv-0.4.1.dist-info/RECORD
