Metadata-Version: 2.1
Name: npv
Version: 0.4.1
Summary: Startup and Corporate Investment and Financial Planning Simulator for Python.
Home-page: http://github.com/mikkokotila
Author: Mikko Kotila
Author-email: mailme@mikkokotila.com
Maintainer: Mikko Kotila
Maintainer-email: mailme@mikkokotila.com
License: MIT
Download-URL: https://github.com/mikkokotila/npvpy
Platform: UNKNOWN
Classifier: Intended Audience :: Science/Research
Classifier: Programming Language :: Python :: 2.7
Classifier: Programming Language :: Python :: 3.4
Classifier: Programming Language :: Python :: 3.5
Classifier: Programming Language :: Python :: 3.6
Classifier: Operating System :: POSIX
Classifier: Operating System :: Unix
Classifier: Operating System :: MacOS
Requires-Dist: wrangle
Requires-Dist: pandas
Requires-Dist: numpy
Requires-Dist: astetik
